aomenc_by_gop/__init__.py
aomenc_by_gop/__main__.py
aomenc_by_gop/app.py
aomenc_by_gop/bin/linux_amd64/onepass_keyframes
aomenc_by_gop/bin/win64/onepass_keyframes.exe
aomenc_by_gop-0.3.0.dist-info/LICENSE
aomenc_by_gop-0.3.0.dist-info/METADATA
aomenc_by_gop-0.3.0.dist-info/WHEEL
aomenc_by_gop-0.3.0.dist-info/entry_points.txt
aomenc_by_gop-0.3.0.dist-info/top_level.txt
aomenc_by_gop-0.3.0.dist-info/RECORD
