Metadata-Version: 2.1
Name: aomenc-by-gop
Version: 0.3.0
Summary: Aomenc by gop
Home-page: https://github.com/wwww-wwww/py-aomenc-by-gop
Author: wwwwwwww
Author-email: wvvwvvvvwvvw@gmail.com
License: UNKNOWN
Platform: UNKNOWN
Classifier: Programming Language :: Python :: 3
Classifier: License :: OSI Approved :: GNU General Public License v3 (GPLv3)
Classifier: Operating System :: OS Independent
Requires-Python: >=3.6
License-File: LICENSE
Requires-Dist: VapourSynth (>=55)
Requires-Dist: rich (>=11.2.0)
